{
    "version": "https://jsonfeed.org/version/1",
    "title": "新浪微博热点",
    "home_page_url": "https://reamd.github.io/wb-top-feed/",
    "feed_url": "https://reamd.github.io/wb-top-feed/rss.json",
    "description": "新浪微博TOP50",
    "items": [
        {
            "id": 1,
            "url": "https://m.weibo.cn/search?containerid=100103type%3D1%26t%3D10%26q%3D%23CCTV6今天播放一条狗的回家路%23",
            "title": "CCTV6今天播放一条狗的回家路"
        },
        {
            "id": 2,
            "url": "https://m.weibo.cn/search?containerid=100103type%3D1%26t%3D10%26q%3D%23特朗普就阿富汗局势炮轰拜登%23",
            "title": "特朗普就阿富汗局势炮轰拜登"
        },
        {
            "id": 3,
            "url": "https://m.weibo.cn/search?containerid=100103type%3D1%26t%3D10%26q%3D%23泫雅金晓钟将合体出道%23",
            "title": "泫雅金晓钟将合体出道"
        },
        {
            "id": 4,
            "url": "https://m.weibo.cn/search?containerid=100103type%3D1%26t%3D10%26q%3D%23权志龙探班jennie%23",
            "title": "权志龙探班jennie"
        },
        {
            "id": 5,
            "url": "https://m.weibo.cn/search?containerid=100103type%3D1%26t%3D10%26q%3D%23阿里女员工被侵害案六大待解疑问%23",
            "title": "阿里女员工被侵害案六大待解疑问"
        },
        {
            "id": 6,
            "url": "https://m.weibo.cn/search?containerid=100103type%3D1%26t%3D10%26q%3D%23外婆借做核酸检测带外孙见爸爸%23",
            "title": "外婆借做核酸检测带外孙见爸爸"
        },
        {
            "id": 7,
            "url": "https://m.weibo.cn/search?containerid=100103type%3D1%26t%3D10%26q%3D%23电影种草官%23",
            "title": "电影种草官"
        },
        {
            "id": 8,
            "url": "https://m.weibo.cn/search?containerid=100103type%3D1%26t%3D10%26q%3D%23程序员手疼7年查出骨肿瘤%23",
            "title": "程序员手疼7年查出骨肿瘤"
        },
        {
            "id": 9,
            "url": "https://m.weibo.cn/search?containerid=100103type%3D1%26t%3D10%26q%3D%23任泽平称生三胎每月奖励三千至五千元%23",
            "title": "任泽平称生三胎每月奖励三千至五千元"
        },
        {
            "id": 10,
            "url": "https://m.weibo.cn/search?containerid=100103type%3D1%26t%3D10%26q%3D%23济南大润发发臭隔夜肉洗了再卖%23",
            "title": "济南大润发发臭隔夜肉洗了再卖"
        },
        {
            "id": 11,
            "url": "https://m.weibo.cn/search?containerid=100103type%3D1%26t%3D10%26q%3D%23全运会%23",
            "title": "全运会"
        },
        {
            "id": 12,
            "url": "https://m.weibo.cn/search?containerid=100103type%3D1%26t%3D10%26q%3D%23泫雅一天要晕倒好几次%23",
            "title": "泫雅一天要晕倒好几次"
        },
        {
            "id": 13,
            "url": "https://m.weibo.cn/search?containerid=100103type%3D1%26t%3D10%26q%3D%23阿富汗总统已逃离喀布尔%23",
            "title": "阿富汗总统已逃离喀布尔"
        },
        {
            "id": 14,
            "url": "https://m.weibo.cn/search?containerid=100103type%3D1%26t%3D10%26q%3D%23塔利班希望阿富汗逃亡民众留下来%23",
            "title": "塔利班希望阿富汗逃亡民众留下来"
        },
        {
            "id": 15,
            "url": "https://m.weibo.cn/search?containerid=100103type%3D1%26t%3D10%26q%3D%23一部电视剧长达807集%23",
            "title": "一部电视剧长达807集"
        },
        {
            "id": 16,
            "url": "https://m.weibo.cn/search?containerid=100103type%3D1%26t%3D10%26q%3D%23江苏疫情%23",
            "title": "江苏疫情"
        },
        {
            "id": 17,
            "url": "https://m.weibo.cn/search?containerid=100103type%3D1%26t%3D10%26q%3D%23你是我的荣耀%23",
            "title": "你是我的荣耀"
        },
        {
            "id": 18,
            "url": "https://m.weibo.cn/search?containerid=100103type%3D1%26t%3D10%26q%3D%23巩立姣说自己敷面膜又白回来啦%23",
            "title": "巩立姣说自己敷面膜又白回来啦"
        },
        {
            "id": 19,
            "url": "https://m.weibo.cn/search?containerid=100103type%3D1%26t%3D10%26q%3D%23拳力以赴的我们阵容官宣%23",
            "title": "拳力以赴的我们阵容官宣"
        },
        {
            "id": 20,
            "url": "https://m.weibo.cn/search?containerid=100103type%3D1%26t%3D10%26q%3D%23上海地铁%23",
            "title": "上海地铁"
        },
        {
            "id": 21,
            "url": "https://m.weibo.cn/search?containerid=100103type%3D1%26t%3D10%26q%3D%23当你突然没化妆%23",
            "title": "当你突然没化妆"
        },
        {
            "id": 22,
            "url": "https://m.weibo.cn/search?containerid=100103type%3D1%26t%3D10%26q%3D%23女子想支持国货嫌贵偷新鞋被抓%23",
            "title": "女子想支持国货嫌贵偷新鞋被抓"
        },
        {
            "id": 23,
            "url": "https://m.weibo.cn/search?containerid=100103type%3D1%26t%3D10%26q%3D%23全爸希望全红婵未来能够上大学%23",
            "title": "全爸希望全红婵未来能够上大学"
        },
        {
            "id": 24,
            "url": "https://m.weibo.cn/search?containerid=100103type%3D1%26t%3D10%26q%3D%23塔利班宣布攻占总统府%23",
            "title": "塔利班宣布攻占总统府"
        },
        {
            "id": 25,
            "url": "https://m.weibo.cn/search?containerid=100103type%3D1%26t%3D10%26q%3D%23陈奕迅不期而遇的夏天%23",
            "title": "陈奕迅不期而遇的夏天"
        },
        {
            "id": 26,
            "url": "https://m.weibo.cn/search?containerid=100103type%3D1%26t%3D10%26q%3D%23安徽欺凌事件10名违法行为人被处罚%23",
            "title": "安徽欺凌事件10名违法行为人被处罚"
        },
        {
            "id": 27,
            "url": "https://m.weibo.cn/search?containerid=100103type%3D1%26t%3D10%26q%3D%23玉楼春女子群像大片%23",
            "title": "玉楼春女子群像大片"
        },
        {
            "id": 28,
            "url": "https://m.weibo.cn/search?containerid=100103type%3D1%26t%3D10%26q%3D%23英孚教育称愿接纳华尔街英语学员%23",
            "title": "英孚教育称愿接纳华尔街英语学员"
        },
        {
            "id": 29,
            "url": "https://m.weibo.cn/search?containerid=100103type%3D1%26t%3D10%26q%3D%23人民日报谈网络欺凌现象%23",
            "title": "人民日报谈网络欺凌现象"
        },
        {
            "id": 30,
            "url": "https://m.weibo.cn/search?containerid=100103type%3D1%26t%3D10%26q%3D%23原来这才是真正的蛙泳%23",
            "title": "原来这才是真正的蛙泳"
        },
        {
            "id": 31,
            "url": "https://m.weibo.cn/search?containerid=100103type%3D1%26t%3D10%26q%3D%23乔峰接任丐帮帮主%23",
            "title": "乔峰接任丐帮帮主"
        },
        {
            "id": 32,
            "url": "https://m.weibo.cn/search?containerid=100103type%3D1%26t%3D10%26q%3D%2317岁时的蔡徐坤%23",
            "title": "17岁时的蔡徐坤"
        },
        {
            "id": 33,
            "url": "https://m.weibo.cn/search?containerid=100103type%3D1%26t%3D10%26q%3D%23原来下午茶文化起源中国%23",
            "title": "原来下午茶文化起源中国"
        },
        {
            "id": 34,
            "url": "https://m.weibo.cn/search?containerid=100103type%3D1%26t%3D10%26q%3D%23全红婵水花消失术是怎样炼成的%23",
            "title": "全红婵水花消失术是怎样炼成的"
        },
        {
            "id": 35,
            "url": "https://m.weibo.cn/search?containerid=100103type%3D1%26t%3D10%26q%3D%23为什么大领导大多都很和善%23",
            "title": "为什么大领导大多都很和善"
        },
        {
            "id": 36,
            "url": "https://m.weibo.cn/search?containerid=100103type%3D1%26t%3D10%26q%3D%23小米汽车总部将落户北京%23",
            "title": "小米汽车总部将落户北京"
        },
        {
            "id": 37,
            "url": "https://m.weibo.cn/search?containerid=100103type%3D1%26t%3D10%26q%3D%23感染炭疽病毒什么症状%23",
            "title": "感染炭疽病毒什么症状"
        },
        {
            "id": 38,
            "url": "https://m.weibo.cn/search?containerid=100103type%3D1%26t%3D10%26q%3D%23北京大中小学幼儿园如期开学%23",
            "title": "北京大中小学幼儿园如期开学"
        },
        {
            "id": 39,
            "url": "https://m.weibo.cn/search?containerid=100103type%3D1%26t%3D10%26q%3D%23阴阳师绘世花鸟卷%23",
            "title": "阴阳师绘世花鸟卷"
        },
        {
            "id": 40,
            "url": "https://m.weibo.cn/search?containerid=100103type%3D1%26t%3D10%26q%3D%23两弹一星元勋于敏诞辰%23",
            "title": "两弹一星元勋于敏诞辰"
        },
        {
            "id": 41,
            "url": "https://m.weibo.cn/search?containerid=100103type%3D1%26t%3D10%26q%3D%235.6万只盐水鸭到达禄口封控区%23",
            "title": "5.6万只盐水鸭到达禄口封控区"
        },
        {
            "id": 42,
            "url": "https://m.weibo.cn/search?containerid=100103type%3D1%26t%3D10%26q%3D%23粉丝写给严浩翔的生日信%23",
            "title": "粉丝写给严浩翔的生日信"
        },
        {
            "id": 43,
            "url": "https://m.weibo.cn/search?containerid=100103type%3D1%26t%3D10%26q%3D%23塔利班发言人称在阿富汗战争已结束%23",
            "title": "塔利班发言人称在阿富汗战争已结束"
        },
        {
            "id": 44,
            "url": "https://m.weibo.cn/search?containerid=100103type%3D1%26t%3D10%26q%3D%23许昕的擦汗动作%23",
            "title": "许昕的擦汗动作"
        },
        {
            "id": 45,
            "url": "https://m.weibo.cn/search?containerid=100103type%3D1%26t%3D10%26q%3D%23300元一根的上头电子烟成本仅几十%23",
            "title": "300元一根的上头电子烟成本仅几十"
        },
        {
            "id": 46,
            "url": "https://m.weibo.cn/search?containerid=100103type%3D1%26t%3D10%26q%3D%23玉楼春%23",
            "title": "玉楼春"
        },
        {
            "id": 47,
            "url": "https://m.weibo.cn/search?containerid=100103type%3D1%26t%3D10%26q%3D%23河南新增6例本土确诊%23",
            "title": "河南新增6例本土确诊"
        },
        {
            "id": 48,
            "url": "https://m.weibo.cn/search?containerid=100103type%3D1%26t%3D10%26q%3D%23实拍阿富汗首都混乱一天%23",
            "title": "实拍阿富汗首都混乱一天"
        },
        {
            "id": 49,
            "url": "https://m.weibo.cn/search?containerid=100103type%3D1%26t%3D10%26q%3D%23女子将10年校园欺凌经历做成桌游%23",
            "title": "女子将10年校园欺凌经历做成桌游"
        },
        {
            "id": 50,
            "url": "https://m.weibo.cn/search?containerid=100103type%3D1%26t%3D10%26q%3D%23江苏新增6例本土确诊病例%23",
            "title": "江苏新增6例本土确诊病例"
        }
    ]
}