{
    "version": "https://jsonfeed.org/version/1",
    "title": "新浪微博热点",
    "home_page_url": "https://reamd.github.io/wb-top-feed/",
    "feed_url": "https://reamd.github.io/wb-top-feed/rss.json",
    "description": "新浪微博TOP50",
    "items": [
        {
            "id": 1,
            "url": "https://m.weibo.cn/search?containerid=100103type%3D1%26t%3D10%26q%3D%23腾讯宣布再投500亿元助力共同富裕%23",
            "title": "腾讯宣布再投500亿元助力共同富裕"
        },
        {
            "id": 2,
            "url": "https://m.weibo.cn/search?containerid=100103type%3D1%26t%3D10%26q%3D%23拜登支持率降至上任以来最低%23",
            "title": "拜登支持率降至上任以来最低"
        },
        {
            "id": 3,
            "url": "https://m.weibo.cn/search?containerid=100103type%3D1%26t%3D10%26q%3D%23古剑奇谭%23",
            "title": "古剑奇谭"
        },
        {
            "id": 4,
            "url": "https://m.weibo.cn/search?containerid=100103type%3D1%26t%3D10%26q%3D%23费启鸣爆款清单%23",
            "title": "费启鸣爆款清单"
        },
        {
            "id": 5,
            "url": "https://m.weibo.cn/search?containerid=100103type%3D1%26t%3D10%26q%3D%23斯嘉丽约翰逊生下二胎%23",
            "title": "斯嘉丽约翰逊生下二胎"
        },
        {
            "id": 6,
            "url": "https://m.weibo.cn/search?containerid=100103type%3D1%26t%3D10%26q%3D%23阿富汗女孩哭求美军放行%23",
            "title": "阿富汗女孩哭求美军放行"
        },
        {
            "id": 7,
            "url": "https://m.weibo.cn/search?containerid=100103type%3D1%26t%3D10%26q%3D%23杭州警方通报六旬男子捅死29岁男子%23",
            "title": "杭州警方通报六旬男子捅死29岁男子"
        },
        {
            "id": 8,
            "url": "https://m.weibo.cn/search?containerid=100103type%3D1%26t%3D10%26q%3D%23日本东京湾发现残奥会保安浮尸%23",
            "title": "日本东京湾发现残奥会保安浮尸"
        },
        {
            "id": 9,
            "url": "https://m.weibo.cn/search?containerid=100103type%3D1%26t%3D10%26q%3D%23披荆斩棘的姐姐们颜值有多绝%23",
            "title": "披荆斩棘的姐姐们颜值有多绝"
        },
        {
            "id": 10,
            "url": "https://m.weibo.cn/search?containerid=100103type%3D1%26t%3D10%26q%3D%23浙江卫视的彩蛋是周杰伦%23",
            "title": "浙江卫视的彩蛋是周杰伦"
        },
        {
            "id": 11,
            "url": "https://m.weibo.cn/search?containerid=100103type%3D1%26t%3D10%26q%3D%23微博情绪%23",
            "title": "微博情绪"
        },
        {
            "id": 12,
            "url": "https://m.weibo.cn/search?containerid=100103type%3D1%26t%3D10%26q%3D%23孟晚舟引渡案将于10月21日裁决%23",
            "title": "孟晚舟引渡案将于10月21日裁决"
        },
        {
            "id": 13,
            "url": "https://m.weibo.cn/search?containerid=100103type%3D1%26t%3D10%26q%3D%23吉娜开口就是老妹儿啊%23",
            "title": "吉娜开口就是老妹儿啊"
        },
        {
            "id": 14,
            "url": "https://m.weibo.cn/search?containerid=100103type%3D1%26t%3D10%26q%3D%23apex%23",
            "title": "apex"
        },
        {
            "id": 15,
            "url": "https://m.weibo.cn/search?containerid=100103type%3D1%26t%3D10%26q%3D%23不太知名但是很美的小城市%23",
            "title": "不太知名但是很美的小城市"
        },
        {
            "id": 16,
            "url": "https://m.weibo.cn/search?containerid=100103type%3D1%26t%3D10%26q%3D%23庆祝西藏和平解放70周年大会%23",
            "title": "庆祝西藏和平解放70周年大会"
        },
        {
            "id": 17,
            "url": "https://m.weibo.cn/search?containerid=100103type%3D1%26t%3D10%26q%3D%23陈露方否认索要分手费%23",
            "title": "陈露方否认索要分手费"
        },
        {
            "id": 18,
            "url": "https://m.weibo.cn/search?containerid=100103type%3D1%26t%3D10%26q%3D%23章若楠演的公主病%23",
            "title": "章若楠演的公主病"
        },
        {
            "id": 19,
            "url": "https://m.weibo.cn/search?containerid=100103type%3D1%26t%3D10%26q%3D%23心动的信号真心话好刺激%23",
            "title": "心动的信号真心话好刺激"
        },
        {
            "id": 20,
            "url": "https://m.weibo.cn/search?containerid=100103type%3D1%26t%3D10%26q%3D%23KK 很抱歉让大家这么生气%23",
            "title": "KK 很抱歉让大家这么生气"
        },
        {
            "id": 21,
            "url": "https://m.weibo.cn/search?containerid=100103type%3D1%26t%3D10%26q%3D%23上海研发支架口罩戴眼镜不起雾%23",
            "title": "上海研发支架口罩戴眼镜不起雾"
        },
        {
            "id": 22,
            "url": "https://m.weibo.cn/search?containerid=100103type%3D1%26t%3D10%26q%3D%23孟晚舟未给汇丰造成任何损失%23",
            "title": "孟晚舟未给汇丰造成任何损失"
        },
        {
            "id": 23,
            "url": "https://m.weibo.cn/search?containerid=100103type%3D1%26t%3D10%26q%3D%23马伯骞 感情中没有时间轴%23",
            "title": "马伯骞 感情中没有时间轴"
        },
        {
            "id": 24,
            "url": "https://m.weibo.cn/search?containerid=100103type%3D1%26t%3D10%26q%3D%23angelababy担心洪成成变得胆怯%23",
            "title": "angelababy担心洪成成变得胆怯"
        },
        {
            "id": 25,
            "url": "https://m.weibo.cn/search?containerid=100103type%3D1%26t%3D10%26q%3D%23白鹿高质量端水大师%23",
            "title": "白鹿高质量端水大师"
        },
        {
            "id": 26,
            "url": "https://m.weibo.cn/search?containerid=100103type%3D1%26t%3D10%26q%3D%23骗子对民警说找到我就嫁给你%23",
            "title": "骗子对民警说找到我就嫁给你"
        },
        {
            "id": 27,
            "url": "https://m.weibo.cn/search?containerid=100103type%3D1%26t%3D10%26q%3D%23朴树谈粉籍%23",
            "title": "朴树谈粉籍"
        },
        {
            "id": 28,
            "url": "https://m.weibo.cn/search?containerid=100103type%3D1%26t%3D10%26q%3D%232人留守封控村照顾全村猫狗鸡鸭鱼%23",
            "title": "2人留守封控村照顾全村猫狗鸡鸭鱼"
        },
        {
            "id": 29,
            "url": "https://m.weibo.cn/search?containerid=100103type%3D1%26t%3D10%26q%3D%23被豆豆笑死了%23",
            "title": "被豆豆笑死了"
        },
        {
            "id": 30,
            "url": "https://m.weibo.cn/search?containerid=100103type%3D1%26t%3D10%26q%3D%23让尊医成为自觉%23",
            "title": "让尊医成为自觉"
        },
        {
            "id": 31,
            "url": "https://m.weibo.cn/search?containerid=100103type%3D1%26t%3D10%26q%3D%23他们救人的战场不止在医院%23",
            "title": "他们救人的战场不止在医院"
        },
        {
            "id": 32,
            "url": "https://m.weibo.cn/search?containerid=100103type%3D1%26t%3D10%26q%3D%23孟晚舟%23",
            "title": "孟晚舟"
        },
        {
            "id": 33,
            "url": "https://m.weibo.cn/search?containerid=100103type%3D1%26t%3D10%26q%3D%23日本动漫产业销售额十年来首降%23",
            "title": "日本动漫产业销售额十年来首降"
        },
        {
            "id": 34,
            "url": "https://m.weibo.cn/search?containerid=100103type%3D1%26t%3D10%26q%3D%23陈思铭重现赵琦君名场面%23",
            "title": "陈思铭重现赵琦君名场面"
        },
        {
            "id": 35,
            "url": "https://m.weibo.cn/search?containerid=100103type%3D1%26t%3D10%26q%3D%23近2万名干警向纪委监委投案%23",
            "title": "近2万名干警向纪委监委投案"
        },
        {
            "id": 36,
            "url": "https://m.weibo.cn/search?containerid=100103type%3D1%26t%3D10%26q%3D%23海霞说别把劳动者困于系统绑于算法%23",
            "title": "海霞说别把劳动者困于系统绑于算法"
        },
        {
            "id": 37,
            "url": "https://m.weibo.cn/search?containerid=100103type%3D1%26t%3D10%26q%3D%23郭麒麟 彼此的爱要互相看到%23",
            "title": "郭麒麟 彼此的爱要互相看到"
        },
        {
            "id": 38,
            "url": "https://m.weibo.cn/search?containerid=100103type%3D1%26t%3D10%26q%3D%23大江好可爱%23",
            "title": "大江好可爱"
        },
        {
            "id": 39,
            "url": "https://m.weibo.cn/search?containerid=100103type%3D1%26t%3D10%26q%3D%23一生一世%23",
            "title": "一生一世"
        },
        {
            "id": 40,
            "url": "https://m.weibo.cn/search?containerid=100103type%3D1%26t%3D10%26q%3D%23一公司老板禁止员工热饭%23",
            "title": "一公司老板禁止员工热饭"
        },
        {
            "id": 41,
            "url": "https://m.weibo.cn/search?containerid=100103type%3D1%26t%3D10%26q%3D%23阿富汗前副总统自封临时总统%23",
            "title": "阿富汗前副总统自封临时总统"
        },
        {
            "id": 42,
            "url": "https://m.weibo.cn/search?containerid=100103type%3D1%26t%3D10%26q%3D%23毛阿敏 跑调%23",
            "title": "毛阿敏 跑调"
        },
        {
            "id": 43,
            "url": "https://m.weibo.cn/search?containerid=100103type%3D1%26t%3D10%26q%3D%23哪些植物吃了会躺板板%23",
            "title": "哪些植物吃了会躺板板"
        },
        {
            "id": 44,
            "url": "https://m.weibo.cn/search?containerid=100103type%3D1%26t%3D10%26q%3D%23我国成功发射天绘二号02组卫星%23",
            "title": "我国成功发射天绘二号02组卫星"
        },
        {
            "id": 45,
            "url": "https://m.weibo.cn/search?containerid=100103type%3D1%26t%3D10%26q%3D%23公交司机吵架后要与乘客同归于尽%23",
            "title": "公交司机吵架后要与乘客同归于尽"
        },
        {
            "id": 46,
            "url": "https://m.weibo.cn/search?containerid=100103type%3D1%26t%3D10%26q%3D%23周深琵琶对唱大鱼%23",
            "title": "周深琵琶对唱大鱼"
        },
        {
            "id": 47,
            "url": "https://m.weibo.cn/search?containerid=100103type%3D1%26t%3D10%26q%3D%23宋亚轩wave%23",
            "title": "宋亚轩wave"
        },
        {
            "id": 48,
            "url": "https://m.weibo.cn/search?containerid=100103type%3D1%26t%3D10%26q%3D%23上海确诊病例14天内未离沪%23",
            "title": "上海确诊病例14天内未离沪"
        },
        {
            "id": 49,
            "url": "https://m.weibo.cn/search?containerid=100103type%3D1%26t%3D10%26q%3D%23男子出车祸接孕妻电话求消防别出声%23",
            "title": "男子出车祸接孕妻电话求消防别出声"
        },
        {
            "id": 50,
            "url": "https://m.weibo.cn/search?containerid=100103type%3D1%26t%3D10%26q%3D%23周生辰人设%23",
            "title": "周生辰人设"
        }
    ]
}