{
    "version": "https://jsonfeed.org/version/1",
    "title": "新浪微博热点",
    "home_page_url": "https://reamd.github.io/wb-top-feed/",
    "feed_url": "https://reamd.github.io/wb-top-feed/rss.json",
    "description": "新浪微博TOP50",
    "items": [
        {
            "id": 1,
            "url": "https://m.weibo.cn/search?containerid=100103type%3D1%26t%3D10%26q%3D%232人同桌饮酒分开后警车内又碰面%23",
            "title": "2人同桌饮酒分开后警车内又碰面"
        },
        {
            "id": 2,
            "url": "https://m.weibo.cn/search?containerid=100103type%3D1%26t%3D10%26q%3D%23美国国防部回应喀布尔机场惨案%23",
            "title": "美国国防部回应喀布尔机场惨案"
        },
        {
            "id": 3,
            "url": "https://m.weibo.cn/search?containerid=100103type%3D1%26t%3D10%26q%3D%23原来周字里面是个土%23",
            "title": "原来周字里面是个土"
        },
        {
            "id": 4,
            "url": "https://m.weibo.cn/search?containerid=100103type%3D1%26t%3D10%26q%3D%23林墨 没在怕的%23",
            "title": "林墨 没在怕的"
        },
        {
            "id": 5,
            "url": "https://m.weibo.cn/search?containerid=100103type%3D1%26t%3D10%26q%3D%23黄晓明终究是被磨平了棱角%23",
            "title": "黄晓明终究是被磨平了棱角"
        },
        {
            "id": 6,
            "url": "https://m.weibo.cn/search?containerid=100103type%3D1%26t%3D10%26q%3D%23女子网恋被骗32万网上找律师被骗4万%23",
            "title": "女子网恋被骗32万网上找律师被骗4万"
        },
        {
            "id": 7,
            "url": "https://m.weibo.cn/search?containerid=100103type%3D1%26t%3D10%26q%3D%23儿童药物将无针注射%23",
            "title": "儿童药物将无针注射"
        },
        {
            "id": 8,
            "url": "https://m.weibo.cn/search?containerid=100103type%3D1%26t%3D10%26q%3D%23女生看了都会沉默%23",
            "title": "女生看了都会沉默"
        },
        {
            "id": 9,
            "url": "https://m.weibo.cn/search?containerid=100103type%3D1%26t%3D10%26q%3D%23樊振东回应不玩社交媒体%23",
            "title": "樊振东回应不玩社交媒体"
        },
        {
            "id": 10,
            "url": "https://m.weibo.cn/search?containerid=100103type%3D1%26t%3D10%26q%3D%23女子花15万购买心灵课程疑被骗%23",
            "title": "女子花15万购买心灵课程疑被骗"
        },
        {
            "id": 11,
            "url": "https://m.weibo.cn/search?containerid=100103type%3D1%26t%3D10%26q%3D%23毛晓彤说越懂事的姑娘越让人心疼%23",
            "title": "毛晓彤说越懂事的姑娘越让人心疼"
        },
        {
            "id": 12,
            "url": "https://m.weibo.cn/search?containerid=100103type%3D1%26t%3D10%26q%3D%23杨幂 纹身贴%23",
            "title": "杨幂 纹身贴"
        },
        {
            "id": 13,
            "url": "https://m.weibo.cn/search?containerid=100103type%3D1%26t%3D10%26q%3D%23杨洋的笑点到底有多低%23",
            "title": "杨洋的笑点到底有多低"
        },
        {
            "id": 14,
            "url": "https://m.weibo.cn/search?containerid=100103type%3D1%26t%3D10%26q%3D%23被孙兴气死%23",
            "title": "被孙兴气死"
        },
        {
            "id": 15,
            "url": "https://m.weibo.cn/search?containerid=100103type%3D1%26t%3D10%26q%3D%23塔利班扮演记者街头采访民众%23",
            "title": "塔利班扮演记者街头采访民众"
        },
        {
            "id": 16,
            "url": "https://m.weibo.cn/search?containerid=100103type%3D1%26t%3D10%26q%3D%23糖尿病患者怎么吃最科学%23",
            "title": "糖尿病患者怎么吃最科学"
        },
        {
            "id": 17,
            "url": "https://m.weibo.cn/search?containerid=100103type%3D1%26t%3D10%26q%3D%23阿富汗女导演街头疾呼逃离塔利班%23",
            "title": "阿富汗女导演街头疾呼逃离塔利班"
        },
        {
            "id": 18,
            "url": "https://m.weibo.cn/search?containerid=100103type%3D1%26t%3D10%26q%3D%23脱口秀大会%23",
            "title": "脱口秀大会"
        },
        {
            "id": 19,
            "url": "https://m.weibo.cn/search?containerid=100103type%3D1%26t%3D10%26q%3D%23诗幂%23",
            "title": "诗幂"
        },
        {
            "id": 20,
            "url": "https://m.weibo.cn/search?containerid=100103type%3D1%26t%3D10%26q%3D%23深圳顶级学区房频频流拍%23",
            "title": "深圳顶级学区房频频流拍"
        },
        {
            "id": 21,
            "url": "https://m.weibo.cn/search?containerid=100103type%3D1%26t%3D10%26q%3D%23大妈拒扫健康码还一巴掌抡倒防疫人员%23",
            "title": "大妈拒扫健康码还一巴掌抡倒防疫人员"
        },
        {
            "id": 22,
            "url": "https://m.weibo.cn/search?containerid=100103type%3D1%26t%3D10%26q%3D%23赵珂晒与张继科合照%23",
            "title": "赵珂晒与张继科合照"
        },
        {
            "id": 23,
            "url": "https://m.weibo.cn/search?containerid=100103type%3D1%26t%3D10%26q%3D%23魏大勋感谢爸爸在自己要放弃时说坚持%23",
            "title": "魏大勋感谢爸爸在自己要放弃时说坚持"
        },
        {
            "id": 24,
            "url": "https://m.weibo.cn/search?containerid=100103type%3D1%26t%3D10%26q%3D%23吉林大学回应宿舍甲醛超标%23",
            "title": "吉林大学回应宿舍甲醛超标"
        },
        {
            "id": 25,
            "url": "https://m.weibo.cn/search?containerid=100103type%3D1%26t%3D10%26q%3D%23孙千哭戏%23",
            "title": "孙千哭戏"
        },
        {
            "id": 26,
            "url": "https://m.weibo.cn/search?containerid=100103type%3D1%26t%3D10%26q%3D%23杨笠 以后只调侃成功的男性%23",
            "title": "杨笠 以后只调侃成功的男性"
        },
        {
            "id": 27,
            "url": "https://m.weibo.cn/search?containerid=100103type%3D1%26t%3D10%26q%3D%23每晚6点到8点的西安钟楼绝美%23",
            "title": "每晚6点到8点的西安钟楼绝美"
        },
        {
            "id": 28,
            "url": "https://m.weibo.cn/search?containerid=100103type%3D1%26t%3D10%26q%3D%23男子替狗报仇扎宝马车胎%23",
            "title": "男子替狗报仇扎宝马车胎"
        },
        {
            "id": 29,
            "url": "https://m.weibo.cn/search?containerid=100103type%3D1%26t%3D10%26q%3D%23无效上班%23",
            "title": "无效上班"
        },
        {
            "id": 30,
            "url": "https://m.weibo.cn/search?containerid=100103type%3D1%26t%3D10%26q%3D%23美国最大水库一级缺水%23",
            "title": "美国最大水库一级缺水"
        },
        {
            "id": 31,
            "url": "https://m.weibo.cn/search?containerid=100103type%3D1%26t%3D10%26q%3D%235岁女孩用乒乓球精准打纸杯%23",
            "title": "5岁女孩用乒乓球精准打纸杯"
        },
        {
            "id": 32,
            "url": "https://m.weibo.cn/search?containerid=100103type%3D1%26t%3D10%26q%3D%23杨洋于途同框%23",
            "title": "杨洋于途同框"
        },
        {
            "id": 33,
            "url": "https://m.weibo.cn/search?containerid=100103type%3D1%26t%3D10%26q%3D%23美国华盛顿纪念碑遭雷劈%23",
            "title": "美国华盛顿纪念碑遭雷劈"
        },
        {
            "id": 34,
            "url": "https://m.weibo.cn/search?containerid=100103type%3D1%26t%3D10%26q%3D%23敖犬披荆斩棘的哥哥后台花絮%23",
            "title": "敖犬披荆斩棘的哥哥后台花絮"
        },
        {
            "id": 35,
            "url": "https://m.weibo.cn/search?containerid=100103type%3D1%26t%3D10%26q%3D%23周生如故定档%23",
            "title": "周生如故定档"
        },
        {
            "id": 36,
            "url": "https://m.weibo.cn/search?containerid=100103type%3D1%26t%3D10%26q%3D%23许昕马龙最近在看叛逆者%23",
            "title": "许昕马龙最近在看叛逆者"
        },
        {
            "id": 37,
            "url": "https://m.weibo.cn/search?containerid=100103type%3D1%26t%3D10%26q%3D%2312岁杨洋的高质量洗袜子诀窍%23",
            "title": "12岁杨洋的高质量洗袜子诀窍"
        },
        {
            "id": 38,
            "url": "https://m.weibo.cn/search?containerid=100103type%3D1%26t%3D10%26q%3D%23两口子吵架孕妻被扔高速%23",
            "title": "两口子吵架孕妻被扔高速"
        },
        {
            "id": 39,
            "url": "https://m.weibo.cn/search?containerid=100103type%3D1%26t%3D10%26q%3D%23刘奕君剧抛式演技%23",
            "title": "刘奕君剧抛式演技"
        },
        {
            "id": 40,
            "url": "https://m.weibo.cn/search?containerid=100103type%3D1%26t%3D10%26q%3D%23任嘉伦演白鹿师父%23",
            "title": "任嘉伦演白鹿师父"
        },
        {
            "id": 41,
            "url": "https://m.weibo.cn/search?containerid=100103type%3D1%26t%3D10%26q%3D%23神舟十二号航天员将再次出舱%23",
            "title": "神舟十二号航天员将再次出舱"
        },
        {
            "id": 42,
            "url": "https://m.weibo.cn/search?containerid=100103type%3D1%26t%3D10%26q%3D%23最无望的暗恋是什么体验%23",
            "title": "最无望的暗恋是什么体验"
        },
        {
            "id": 43,
            "url": "https://m.weibo.cn/search?containerid=100103type%3D1%26t%3D10%26q%3D%23丈夫瞒着妻子代孕生子妻子不认%23",
            "title": "丈夫瞒着妻子代孕生子妻子不认"
        },
        {
            "id": 44,
            "url": "https://m.weibo.cn/search?containerid=100103type%3D1%26t%3D10%26q%3D%23皮皮虾出拳速度只有千分之二秒%23",
            "title": "皮皮虾出拳速度只有千分之二秒"
        },
        {
            "id": 45,
            "url": "https://m.weibo.cn/search?containerid=100103type%3D1%26t%3D10%26q%3D%23李诞说小佳让脱口秀更有意义%23",
            "title": "李诞说小佳让脱口秀更有意义"
        },
        {
            "id": 46,
            "url": "https://m.weibo.cn/search?containerid=100103type%3D1%26t%3D10%26q%3D%23以为不是在地球%23",
            "title": "以为不是在地球"
        },
        {
            "id": 47,
            "url": "https://m.weibo.cn/search?containerid=100103type%3D1%26t%3D10%26q%3D%23第一次见义勇为就社死了%23",
            "title": "第一次见义勇为就社死了"
        },
        {
            "id": 48,
            "url": "https://m.weibo.cn/search?containerid=100103type%3D1%26t%3D10%26q%3D%23喵咪是如何催促开饭的%23",
            "title": "喵咪是如何催促开饭的"
        },
        {
            "id": 49,
            "url": "https://m.weibo.cn/search?containerid=100103type%3D1%26t%3D10%26q%3D%23教育局通报小学校长猥亵学生事件%23",
            "title": "教育局通报小学校长猥亵学生事件"
        },
        {
            "id": 50,
            "url": "https://m.weibo.cn/search?containerid=100103type%3D1%26t%3D10%26q%3D%23女子实名举报小学时遭校长长期猥亵%23",
            "title": "女子实名举报小学时遭校长长期猥亵"
        }
    ]
}