{
    "version": "https://jsonfeed.org/version/1",
    "title": "新浪微博热点",
    "home_page_url": "https://reamd.github.io/wb-top-feed/",
    "feed_url": "https://reamd.github.io/wb-top-feed/rss.json",
    "description": "新浪微博TOP50",
    "items": [
        {
            "id": 1,
            "url": "https://m.weibo.cn/search?containerid=100103type%3D1%26t%3D10%26q%3D%23东京奥运会闭幕式%23",
            "title": "东京奥运会闭幕式"
        },
        {
            "id": 2,
            "url": "https://m.weibo.cn/search?containerid=100103type%3D1%26t%3D10%26q%3D%23巴黎八分钟%23",
            "title": "巴黎八分钟"
        },
        {
            "id": 3,
            "url": "https://m.weibo.cn/search?containerid=100103type%3D1%26t%3D10%26q%3D%23朱婷奥运期间睡不着觉吃不下饭%23",
            "title": "朱婷奥运期间睡不着觉吃不下饭"
        },
        {
            "id": 4,
            "url": "https://m.weibo.cn/search?containerid=100103type%3D1%26t%3D10%26q%3D%23麦当劳88又又又又来了%23",
            "title": "麦当劳88又又又又来了"
        },
        {
            "id": 5,
            "url": "https://m.weibo.cn/search?containerid=100103type%3D1%26t%3D10%26q%3D%23吴京 收工了%23",
            "title": "吴京 收工了"
        },
        {
            "id": 6,
            "url": "https://m.weibo.cn/search?containerid=100103type%3D1%26t%3D10%26q%3D%23微信表情都戴医用口罩了%23",
            "title": "微信表情都戴医用口罩了"
        },
        {
            "id": 7,
            "url": "https://m.weibo.cn/search?containerid=100103type%3D1%26t%3D10%26q%3D%23连听两遍肯尼亚国歌%23",
            "title": "连听两遍肯尼亚国歌"
        },
        {
            "id": 8,
            "url": "https://m.weibo.cn/search?containerid=100103type%3D1%26t%3D10%26q%3D%23消暑厨艺挑战赛%23",
            "title": "消暑厨艺挑战赛"
        },
        {
            "id": 9,
            "url": "https://m.weibo.cn/search?containerid=100103type%3D1%26t%3D10%26q%3D%23闭幕式放欢乐颂%23",
            "title": "闭幕式放欢乐颂"
        },
        {
            "id": 10,
            "url": "https://m.weibo.cn/search?containerid=100103type%3D1%26t%3D10%26q%3D%23男孩喝鲜羊奶感染布鲁氏菌病%23",
            "title": "男孩喝鲜羊奶感染布鲁氏菌病"
        },
        {
            "id": 11,
            "url": "https://m.weibo.cn/search?containerid=100103type%3D1%26t%3D10%26q%3D%23苏炳添举五星红旗入场%23",
            "title": "苏炳添举五星红旗入场"
        },
        {
            "id": 12,
            "url": "https://m.weibo.cn/search?containerid=100103type%3D1%26t%3D10%26q%3D%23中共中央国务院向中国体育代表团致贺电%23",
            "title": "中共中央国务院向中国体育代表团致贺电"
        },
        {
            "id": 13,
            "url": "https://m.weibo.cn/search?containerid=100103type%3D1%26t%3D10%26q%3D%23上海地铁16号线回应改卧铺呼吁%23",
            "title": "上海地铁16号线回应改卧铺呼吁"
        },
        {
            "id": 14,
            "url": "https://m.weibo.cn/search?containerid=100103type%3D1%26t%3D10%26q%3D%23杨和苏与女友分手%23",
            "title": "杨和苏与女友分手"
        },
        {
            "id": 15,
            "url": "https://m.weibo.cn/search?containerid=100103type%3D1%26t%3D10%26q%3D%23中国人看到大场面就想拍照%23",
            "title": "中国人看到大场面就想拍照"
        },
        {
            "id": 16,
            "url": "https://m.weibo.cn/search?containerid=100103type%3D1%26t%3D10%26q%3D%23郑州一病例核酸检测8次才显阳性%23",
            "title": "郑州一病例核酸检测8次才显阳性"
        },
        {
            "id": 17,
            "url": "https://m.weibo.cn/search?containerid=100103type%3D1%26t%3D10%26q%3D%23中国代表团38金32银18铜收官%23",
            "title": "中国代表团38金32银18铜收官"
        },
        {
            "id": 18,
            "url": "https://m.weibo.cn/search?containerid=100103type%3D1%26t%3D10%26q%3D%23吴克群 yyds是永远都输%23",
            "title": "吴克群 yyds是永远都输"
        },
        {
            "id": 19,
            "url": "https://m.weibo.cn/search?containerid=100103type%3D1%26t%3D10%26q%3D%23被保洁阿姨侧颜惊艳到%23",
            "title": "被保洁阿姨侧颜惊艳到"
        },
        {
            "id": 20,
            "url": "https://m.weibo.cn/search?containerid=100103type%3D1%26t%3D10%26q%3D%23闭幕式灯光拼出奥运五环%23",
            "title": "闭幕式灯光拼出奥运五环"
        },
        {
            "id": 21,
            "url": "https://m.weibo.cn/search?containerid=100103type%3D1%26t%3D10%26q%3D%23梅西哭了%23",
            "title": "梅西哭了"
        },
        {
            "id": 22,
            "url": "https://m.weibo.cn/search?containerid=100103type%3D1%26t%3D10%26q%3D%23哈尔滨一办公楼顶层坍塌已致2人死亡%23",
            "title": "哈尔滨一办公楼顶层坍塌已致2人死亡"
        },
        {
            "id": 23,
            "url": "https://m.weibo.cn/search?containerid=100103type%3D1%26t%3D10%26q%3D%23张大大晒合照为佟丽娅庆生%23",
            "title": "张大大晒合照为佟丽娅庆生"
        },
        {
            "id": 24,
            "url": "https://m.weibo.cn/search?containerid=100103type%3D1%26t%3D10%26q%3D%23中国代表团登场%23",
            "title": "中国代表团登场"
        },
        {
            "id": 25,
            "url": "https://m.weibo.cn/search?containerid=100103type%3D1%26t%3D10%26q%3D%23闭幕式舞蹈看不懂%23",
            "title": "闭幕式舞蹈看不懂"
        },
        {
            "id": 26,
            "url": "https://m.weibo.cn/search?containerid=100103type%3D1%26t%3D10%26q%3D%23奥运会闭幕式响起红莲华%23",
            "title": "奥运会闭幕式响起红莲华"
        },
        {
            "id": 27,
            "url": "https://m.weibo.cn/search?containerid=100103type%3D1%26t%3D10%26q%3D%23李倩说巴黎把银牌换成金的%23",
            "title": "李倩说巴黎把银牌换成金的"
        },
        {
            "id": 28,
            "url": "https://m.weibo.cn/search?containerid=100103type%3D1%26t%3D10%26q%3D%23餐馆让外卖骑手负责盛饭漏盛罚20%23",
            "title": "餐馆让外卖骑手负责盛饭漏盛罚20"
        },
        {
            "id": 29,
            "url": "https://m.weibo.cn/search?containerid=100103type%3D1%26t%3D10%26q%3D%23开始期待冬奥会了%23",
            "title": "开始期待冬奥会了"
        },
        {
            "id": 30,
            "url": "https://m.weibo.cn/search?containerid=100103type%3D1%26t%3D10%26q%3D%23郎平说鸡汤总有喝腻的时候%23",
            "title": "郎平说鸡汤总有喝腻的时候"
        },
        {
            "id": 31,
            "url": "https://m.weibo.cn/search?containerid=100103type%3D1%26t%3D10%26q%3D%23闭幕式像极了广场舞%23",
            "title": "闭幕式像极了广场舞"
        },
        {
            "id": 32,
            "url": "https://m.weibo.cn/search?containerid=100103type%3D1%26t%3D10%26q%3D%23铁路空姐一天装卸100多个集装箱%23",
            "title": "铁路空姐一天装卸100多个集装箱"
        },
        {
            "id": 33,
            "url": "https://m.weibo.cn/search?containerid=100103type%3D1%26t%3D10%26q%3D%23马拉松铜牌得主穿的是匹克%23",
            "title": "马拉松铜牌得主穿的是匹克"
        },
        {
            "id": 34,
            "url": "https://m.weibo.cn/search?containerid=100103type%3D1%26t%3D10%26q%3D%23郑州新增无症状感染者转确诊40例%23",
            "title": "郑州新增无症状感染者转确诊40例"
        },
        {
            "id": 35,
            "url": "https://m.weibo.cn/search?containerid=100103type%3D1%26t%3D10%26q%3D%23与君歌%23",
            "title": "与君歌"
        },
        {
            "id": 36,
            "url": "https://m.weibo.cn/search?containerid=100103type%3D1%26t%3D10%26q%3D%23闭幕式短片里的中国运动员%23",
            "title": "闭幕式短片里的中国运动员"
        },
        {
            "id": 37,
            "url": "https://m.weibo.cn/search?containerid=100103type%3D1%26t%3D10%26q%3D%23广西一老汉当街持斧砍人后潜逃%23",
            "title": "广西一老汉当街持斧砍人后潜逃"
        },
        {
            "id": 38,
            "url": "https://m.weibo.cn/search?containerid=100103type%3D1%26t%3D10%26q%3D%23东京巴黎交接奥运旗帜%23",
            "title": "东京巴黎交接奥运旗帜"
        },
        {
            "id": 39,
            "url": "https://m.weibo.cn/search?containerid=100103type%3D1%26t%3D10%26q%3D%23中国军团奥运夺金水墨画%23",
            "title": "中国军团奥运夺金水墨画"
        },
        {
            "id": 40,
            "url": "https://m.weibo.cn/search?containerid=100103type%3D1%26t%3D10%26q%3D%23我们会铭记有过这么一个夏天%23",
            "title": "我们会铭记有过这么一个夏天"
        },
        {
            "id": 41,
            "url": "https://m.weibo.cn/search?containerid=100103type%3D1%26t%3D10%26q%3D%23李九解说%23",
            "title": "李九解说"
        },
        {
            "id": 42,
            "url": "https://m.weibo.cn/search?containerid=100103type%3D1%26t%3D10%26q%3D%23四川暴雨致部分列车停运%23",
            "title": "四川暴雨致部分列车停运"
        },
        {
            "id": 43,
            "url": "https://m.weibo.cn/search?containerid=100103type%3D1%26t%3D10%26q%3D%23中国足球事业发展战略与对策研究%23",
            "title": "中国足球事业发展战略与对策研究"
        },
        {
            "id": 44,
            "url": "https://m.weibo.cn/search?containerid=100103type%3D1%26t%3D10%26q%3D%23FPX EDG%23",
            "title": "FPX EDG"
        },
        {
            "id": 45,
            "url": "https://m.weibo.cn/search?containerid=100103type%3D1%26t%3D10%26q%3D%23致敬为中国拼搏的运动员们%23",
            "title": "致敬为中国拼搏的运动员们"
        },
        {
            "id": 46,
            "url": "https://m.weibo.cn/search?containerid=100103type%3D1%26t%3D10%26q%3D%23法国宇航员空间站吹萨克斯%23",
            "title": "法国宇航员空间站吹萨克斯"
        },
        {
            "id": 47,
            "url": "https://m.weibo.cn/search?containerid=100103type%3D1%26t%3D10%26q%3D%23哈尔滨一办公楼坍塌11人被困%23",
            "title": "哈尔滨一办公楼坍塌11人被困"
        },
        {
            "id": 48,
            "url": "https://m.weibo.cn/search?containerid=100103type%3D1%26t%3D10%26q%3D%23广州塔为奥运健儿爆灯%23",
            "title": "广州塔为奥运健儿爆灯"
        },
        {
            "id": 49,
            "url": "https://m.weibo.cn/search?containerid=100103type%3D1%26t%3D10%26q%3D%23奥运五环上的飞蛾%23",
            "title": "奥运五环上的飞蛾"
        },
        {
            "id": 50,
            "url": "https://m.weibo.cn/search?containerid=100103type%3D1%26t%3D10%26q%3D%23四川地灾橙色预警范围扩大%23",
            "title": "四川地灾橙色预警范围扩大"
        }
    ]
}