{
    "version": "https://jsonfeed.org/version/1",
    "title": "新浪微博热点",
    "home_page_url": "https://reamd.github.io/wb-top-feed/",
    "feed_url": "https://reamd.github.io/wb-top-feed/rss.json",
    "description": "新浪微博TOP50",
    "items": [
        {
            "id": 1,
            "url": "https://m.weibo.cn/search?containerid=100103type%3D1%26t%3D10%26q%3D%23浙江疫情%23",
            "title": "浙江疫情"
        },
        {
            "id": 2,
            "url": "https://m.weibo.cn/search?containerid=100103type%3D1%26t%3D10%26q%3D%23最有排面的求婚小伙要结婚了%23",
            "title": "最有排面的求婚小伙要结婚了"
        },
        {
            "id": 3,
            "url": "https://m.weibo.cn/search?containerid=100103type%3D1%26t%3D10%26q%3D%23大S妈妈称女儿压力很大%23",
            "title": "大S妈妈称女儿压力很大"
        },
        {
            "id": 4,
            "url": "https://m.weibo.cn/search?containerid=100103type%3D1%26t%3D10%26q%3D%23朱天天 聊天语音%23",
            "title": "朱天天 聊天语音"
        },
        {
            "id": 5,
            "url": "https://m.weibo.cn/search?containerid=100103type%3D1%26t%3D10%26q%3D%23朋友建议我以后生孩子一定要剖腹产%23",
            "title": "朋友建议我以后生孩子一定要剖腹产"
        },
        {
            "id": 6,
            "url": "https://m.weibo.cn/search?containerid=100103type%3D1%26t%3D10%26q%3D%23陈键锋教潜水时学员溺亡%23",
            "title": "陈键锋教潜水时学员溺亡"
        },
        {
            "id": 7,
            "url": "https://m.weibo.cn/search?containerid=100103type%3D1%26t%3D10%26q%3D%23和娜扎一起赏雪%23",
            "title": "和娜扎一起赏雪"
        },
        {
            "id": 8,
            "url": "https://m.weibo.cn/search?containerid=100103type%3D1%26t%3D10%26q%3D%23叫姐姐和姐的感觉不一样%23",
            "title": "叫姐姐和姐的感觉不一样"
        },
        {
            "id": 9,
            "url": "https://m.weibo.cn/search?containerid=100103type%3D1%26t%3D10%26q%3D%23朱婷是天选之子吧%23",
            "title": "朱婷是天选之子吧"
        },
        {
            "id": 10,
            "url": "https://m.weibo.cn/search?containerid=100103type%3D1%26t%3D10%26q%3D%23妈妈回应被女儿抱住后放弃气球%23",
            "title": "妈妈回应被女儿抱住后放弃气球"
        },
        {
            "id": 11,
            "url": "https://m.weibo.cn/search?containerid=100103type%3D1%26t%3D10%26q%3D%23第五批国家级非遗名录%23",
            "title": "第五批国家级非遗名录"
        },
        {
            "id": 12,
            "url": "https://m.weibo.cn/search?containerid=100103type%3D1%26t%3D10%26q%3D%23侃爷新恋情%23",
            "title": "侃爷新恋情"
        },
        {
            "id": 13,
            "url": "https://m.weibo.cn/search?containerid=100103type%3D1%26t%3D10%26q%3D%23医生爸太忙买西兰花接高三女儿%23",
            "title": "医生爸太忙买西兰花接高三女儿"
        },
        {
            "id": 14,
            "url": "https://m.weibo.cn/search?containerid=100103type%3D1%26t%3D10%26q%3D%23马嘉祺高考后的第一条微博%23",
            "title": "马嘉祺高考后的第一条微博"
        },
        {
            "id": 15,
            "url": "https://m.weibo.cn/search?containerid=100103type%3D1%26t%3D10%26q%3D%23石家庄一考生走出考场被家人不停投食%23",
            "title": "石家庄一考生走出考场被家人不停投食"
        },
        {
            "id": 16,
            "url": "https://m.weibo.cn/search?containerid=100103type%3D1%26t%3D10%26q%3D%23广州劝返1.8万不符合出行条件人员%23",
            "title": "广州劝返1.8万不符合出行条件人员"
        },
        {
            "id": 17,
            "url": "https://m.weibo.cn/search?containerid=100103type%3D1%26t%3D10%26q%3D%23王冰冰内蒙古分冰%23",
            "title": "王冰冰内蒙古分冰"
        },
        {
            "id": 18,
            "url": "https://m.weibo.cn/search?containerid=100103type%3D1%26t%3D10%26q%3D%23多多时隔三年再演水儿%23",
            "title": "多多时隔三年再演水儿"
        },
        {
            "id": 19,
            "url": "https://m.weibo.cn/search?containerid=100103type%3D1%26t%3D10%26q%3D%23怎么端午节改成送月饼了%23",
            "title": "怎么端午节改成送月饼了"
        },
        {
            "id": 20,
            "url": "https://m.weibo.cn/search?containerid=100103type%3D1%26t%3D10%26q%3D%23浦东一旅客自称核酸阳性致飞机返航%23",
            "title": "浦东一旅客自称核酸阳性致飞机返航"
        },
        {
            "id": 21,
            "url": "https://m.weibo.cn/search?containerid=100103type%3D1%26t%3D10%26q%3D%23端午机票价格跌三成%23",
            "title": "端午机票价格跌三成"
        },
        {
            "id": 22,
            "url": "https://m.weibo.cn/search?containerid=100103type%3D1%26t%3D10%26q%3D%23老板的女儿要我帮她买书%23",
            "title": "老板的女儿要我帮她买书"
        },
        {
            "id": 23,
            "url": "https://m.weibo.cn/search?containerid=100103type%3D1%26t%3D10%26q%3D%23嘴巴好看是怎样的体验%23",
            "title": "嘴巴好看是怎样的体验"
        },
        {
            "id": 24,
            "url": "https://m.weibo.cn/search?containerid=100103type%3D1%26t%3D10%26q%3D%23烽火流金%23",
            "title": "烽火流金"
        },
        {
            "id": 25,
            "url": "https://m.weibo.cn/search?containerid=100103type%3D1%26t%3D10%26q%3D%23印度奥委会与李宁解约%23",
            "title": "印度奥委会与李宁解约"
        },
        {
            "id": 26,
            "url": "https://m.weibo.cn/search?containerid=100103type%3D1%26t%3D10%26q%3D%23这猫居然被哄睡着了%23",
            "title": "这猫居然被哄睡着了"
        },
        {
            "id": 27,
            "url": "https://m.weibo.cn/search?containerid=100103type%3D1%26t%3D10%26q%3D%23女子服网购降压药病情更严重%23",
            "title": "女子服网购降压药病情更严重"
        },
        {
            "id": 28,
            "url": "https://m.weibo.cn/search?containerid=100103type%3D1%26t%3D10%26q%3D%23辅警执勤时情绪失控连扇车主3巴掌%23",
            "title": "辅警执勤时情绪失控连扇车主3巴掌"
        },
        {
            "id": 29,
            "url": "https://m.weibo.cn/search?containerid=100103type%3D1%26t%3D10%26q%3D%23毛晓彤星空蓝闪钻抹胸裙%23",
            "title": "毛晓彤星空蓝闪钻抹胸裙"
        },
        {
            "id": 30,
            "url": "https://m.weibo.cn/search?containerid=100103type%3D1%26t%3D10%26q%3D%23易建联郭艾伦王哲林离开国家队%23",
            "title": "易建联郭艾伦王哲林离开国家队"
        },
        {
            "id": 31,
            "url": "https://m.weibo.cn/search?containerid=100103type%3D1%26t%3D10%26q%3D%23中美商务部部长通话%23",
            "title": "中美商务部部长通话"
        },
        {
            "id": 32,
            "url": "https://m.weibo.cn/search?containerid=100103type%3D1%26t%3D10%26q%3D%23人缘好的人都有什么特点%23",
            "title": "人缘好的人都有什么特点"
        },
        {
            "id": 33,
            "url": "https://m.weibo.cn/search?containerid=100103type%3D1%26t%3D10%26q%3D%23肥胖等级如何划分%23",
            "title": "肥胖等级如何划分"
        },
        {
            "id": 34,
            "url": "https://m.weibo.cn/search?containerid=100103type%3D1%26t%3D10%26q%3D%234个人业绩目标4个亿%23",
            "title": "4个人业绩目标4个亿"
        },
        {
            "id": 35,
            "url": "https://m.weibo.cn/search?containerid=100103type%3D1%26t%3D10%26q%3D%23哈工大会发光的录取通知书%23",
            "title": "哈工大会发光的录取通知书"
        },
        {
            "id": 36,
            "url": "https://m.weibo.cn/search?containerid=100103type%3D1%26t%3D10%26q%3D%23神舟十二号将送3名航天员上太空%23",
            "title": "神舟十二号将送3名航天员上太空"
        },
        {
            "id": 37,
            "url": "https://m.weibo.cn/search?containerid=100103type%3D1%26t%3D10%26q%3D%23热依扎吊带红裙造型%23",
            "title": "热依扎吊带红裙造型"
        },
        {
            "id": 38,
            "url": "https://m.weibo.cn/search?containerid=100103type%3D1%26t%3D10%26q%3D%23洛基%23",
            "title": "洛基"
        },
        {
            "id": 39,
            "url": "https://m.weibo.cn/search?containerid=100103type%3D1%26t%3D10%26q%3D%23韩国光州一建筑倒塌致9人死亡%23",
            "title": "韩国光州一建筑倒塌致9人死亡"
        },
        {
            "id": 40,
            "url": "https://m.weibo.cn/search?containerid=100103type%3D1%26t%3D10%26q%3D%23无人机再抓拍北迁象群睡觉%23",
            "title": "无人机再抓拍北迁象群睡觉"
        },
        {
            "id": 41,
            "url": "https://m.weibo.cn/search?containerid=100103type%3D1%26t%3D10%26q%3D%23JBS向黑客支付1100万美元%23",
            "title": "JBS向黑客支付1100万美元"
        },
        {
            "id": 42,
            "url": "https://m.weibo.cn/search?containerid=100103type%3D1%26t%3D10%26q%3D%23高校射艺课1秒被抢完%23",
            "title": "高校射艺课1秒被抢完"
        },
        {
            "id": 43,
            "url": "https://m.weibo.cn/search?containerid=100103type%3D1%26t%3D10%26q%3D%23C罗国家队104球%23",
            "title": "C罗国家队104球"
        },
        {
            "id": 44,
            "url": "https://m.weibo.cn/search?containerid=100103type%3D1%26t%3D10%26q%3D%23高配的siri自带煮水功能%23",
            "title": "高配的siri自带煮水功能"
        },
        {
            "id": 45,
            "url": "https://m.weibo.cn/search?containerid=100103type%3D1%26t%3D10%26q%3D%23假如让郭敬明来写武林外传%23",
            "title": "假如让郭敬明来写武林外传"
        },
        {
            "id": 46,
            "url": "https://m.weibo.cn/search?containerid=100103type%3D1%26t%3D10%26q%3D%23苏炳添百米赛场上的80后%23",
            "title": "苏炳添百米赛场上的80后"
        },
        {
            "id": 47,
            "url": "https://m.weibo.cn/search?containerid=100103type%3D1%26t%3D10%26q%3D%23掘金 太阳%23",
            "title": "掘金 太阳"
        },
        {
            "id": 48,
            "url": "https://m.weibo.cn/search?containerid=100103type%3D1%26t%3D10%26q%3D%233头公象离队或因种群结构调整%23",
            "title": "3头公象离队或因种群结构调整"
        },
        {
            "id": 49,
            "url": "https://m.weibo.cn/search?containerid=100103type%3D1%26t%3D10%26q%3D%23湖南考生出考场连翻两个后空翻%23",
            "title": "湖南考生出考场连翻两个后空翻"
        },
        {
            "id": 50,
            "url": "https://m.weibo.cn/search?containerid=100103type%3D1%26t%3D10%26q%3D%23疫情致印度7500万人跌入贫困%23",
            "title": "疫情致印度7500万人跌入贫困"
        }
    ]
}