{
    "version": "https://jsonfeed.org/version/1",
    "title": "新浪微博热点",
    "home_page_url": "https://reamd.github.io/wb-top-feed/",
    "feed_url": "https://reamd.github.io/wb-top-feed/rss.json",
    "description": "新浪微博TOP50",
    "items": [
        {
            "id": 1,
            "url": "https://m.weibo.cn/search?containerid=100103type%3D1%26t%3D10%26q%3D%23李小鹏 往水里扔个硬币都比她水花大%23",
            "title": "李小鹏 往水里扔个硬币都比她水花大"
        },
        {
            "id": 2,
            "url": "https://m.weibo.cn/search?containerid=100103type%3D1%26t%3D10%26q%3D%23全红婵跳水10米台夺金%23",
            "title": "全红婵跳水10米台夺金"
        },
        {
            "id": 3,
            "url": "https://m.weibo.cn/search?containerid=100103type%3D1%26t%3D10%26q%3D%23国乒女团VS日本女团%23",
            "title": "国乒女团VS日本女团"
        },
        {
            "id": 4,
            "url": "https://m.weibo.cn/search?containerid=100103type%3D1%26t%3D10%26q%3D%23优酸乳青春的酸也很甜%23",
            "title": "优酸乳青春的酸也很甜"
        },
        {
            "id": 5,
            "url": "https://m.weibo.cn/search?containerid=100103type%3D1%26t%3D10%26q%3D%23小S发声%23",
            "title": "小S发声"
        },
        {
            "id": 6,
            "url": "https://m.weibo.cn/search?containerid=100103type%3D1%26t%3D10%26q%3D%23全红婵摘金父亲称全村都在庆祝%23",
            "title": "全红婵摘金父亲称全村都在庆祝"
        },
        {
            "id": 7,
            "url": "https://m.weibo.cn/search?containerid=100103type%3D1%26t%3D10%26q%3D%23杨紫演林之校%23",
            "title": "杨紫演林之校"
        },
        {
            "id": 8,
            "url": "https://m.weibo.cn/search?containerid=100103type%3D1%26t%3D10%26q%3D%23国漫是文化芯片%23",
            "title": "国漫是文化芯片"
        },
        {
            "id": 9,
            "url": "https://m.weibo.cn/search?containerid=100103type%3D1%26t%3D10%26q%3D%2326岁女子经常夜班致2次脑出血%23",
            "title": "26岁女子经常夜班致2次脑出血"
        },
        {
            "id": 10,
            "url": "https://m.weibo.cn/search?containerid=100103type%3D1%26t%3D10%26q%3D%23郭晶晶为全红婵鼓掌%23",
            "title": "郭晶晶为全红婵鼓掌"
        },
        {
            "id": 11,
            "url": "https://m.weibo.cn/search?containerid=100103type%3D1%26t%3D10%26q%3D%23马龙许昕带孩子对比%23",
            "title": "马龙许昕带孩子对比"
        },
        {
            "id": 12,
            "url": "https://m.weibo.cn/search?containerid=100103type%3D1%26t%3D10%26q%3D%23全红婵决赛三跳满分%23",
            "title": "全红婵决赛三跳满分"
        },
        {
            "id": 13,
            "url": "https://m.weibo.cn/search?containerid=100103type%3D1%26t%3D10%26q%3D%23余生请多指教定档%23",
            "title": "余生请多指教定档"
        },
        {
            "id": 14,
            "url": "https://m.weibo.cn/search?containerid=100103type%3D1%26t%3D10%26q%3D%23陈梦王曼昱VS平野美宇石川佳纯%23",
            "title": "陈梦王曼昱VS平野美宇石川佳纯"
        },
        {
            "id": 15,
            "url": "https://m.weibo.cn/search?containerid=100103type%3D1%26t%3D10%26q%3D%23印度选手摘银后的生活变化%23",
            "title": "印度选手摘银后的生活变化"
        },
        {
            "id": 16,
            "url": "https://m.weibo.cn/search?containerid=100103type%3D1%26t%3D10%26q%3D%23罪犯在监狱里能吃到什么%23",
            "title": "罪犯在监狱里能吃到什么"
        },
        {
            "id": 17,
            "url": "https://m.weibo.cn/search?containerid=100103type%3D1%26t%3D10%26q%3D%23陈芋汐女子10米台摘银%23",
            "title": "陈芋汐女子10米台摘银"
        },
        {
            "id": 18,
            "url": "https://m.weibo.cn/search?containerid=100103type%3D1%26t%3D10%26q%3D%23黄晓明主动提议给自己剃头%23",
            "title": "黄晓明主动提议给自己剃头"
        },
        {
            "id": 19,
            "url": "https://m.weibo.cn/search?containerid=100103type%3D1%26t%3D10%26q%3D%23伊藤美诚称对孙颖莎只发挥两三成水平%23",
            "title": "伊藤美诚称对孙颖莎只发挥两三成水平"
        },
        {
            "id": 20,
            "url": "https://m.weibo.cn/search?containerid=100103type%3D1%26t%3D10%26q%3D%23吴敏霞看全红婵激动到尖叫%23",
            "title": "吴敏霞看全红婵激动到尖叫"
        },
        {
            "id": 21,
            "url": "https://m.weibo.cn/search?containerid=100103type%3D1%26t%3D10%26q%3D%23中国跳水和外国跳水%23",
            "title": "中国跳水和外国跳水"
        },
        {
            "id": 22,
            "url": "https://m.weibo.cn/search?containerid=100103type%3D1%26t%3D10%26q%3D%23郑州年龄最小感染者7岁%23",
            "title": "郑州年龄最小感染者7岁"
        },
        {
            "id": 23,
            "url": "https://m.weibo.cn/search?containerid=100103type%3D1%26t%3D10%26q%3D%23武汉海王%23",
            "title": "武汉海王"
        },
        {
            "id": 24,
            "url": "https://m.weibo.cn/search?containerid=100103type%3D1%26t%3D10%26q%3D%23戴利的毛衣织完了%23",
            "title": "戴利的毛衣织完了"
        },
        {
            "id": 25,
            "url": "https://m.weibo.cn/search?containerid=100103type%3D1%26t%3D10%26q%3D%23高敏在全红婵身上看到当年的自己%23",
            "title": "高敏在全红婵身上看到当年的自己"
        },
        {
            "id": 26,
            "url": "https://m.weibo.cn/search?containerid=100103type%3D1%26t%3D10%26q%3D%23北京锤子被申请破产重整%23",
            "title": "北京锤子被申请破产重整"
        },
        {
            "id": 27,
            "url": "https://m.weibo.cn/search?containerid=100103type%3D1%26t%3D10%26q%3D%23全红婵一天训练要跳400多次%23",
            "title": "全红婵一天训练要跳400多次"
        },
        {
            "id": 28,
            "url": "https://m.weibo.cn/search?containerid=100103type%3D1%26t%3D10%26q%3D%23女子利用变声器骗闺蜜320万%23",
            "title": "女子利用变声器骗闺蜜320万"
        },
        {
            "id": 29,
            "url": "https://m.weibo.cn/search?containerid=100103type%3D1%26t%3D10%26q%3D%23东京奥运中国队已9次包揽金银%23",
            "title": "东京奥运中国队已9次包揽金银"
        },
        {
            "id": 30,
            "url": "https://m.weibo.cn/search?containerid=100103type%3D1%26t%3D10%26q%3D%23日本选手竞走姿势%23",
            "title": "日本选手竞走姿势"
        },
        {
            "id": 31,
            "url": "https://m.weibo.cn/search?containerid=100103type%3D1%26t%3D10%26q%3D%23本轮疫情2至3个潜伏期内基本可控%23",
            "title": "本轮疫情2至3个潜伏期内基本可控"
        },
        {
            "id": 32,
            "url": "https://m.weibo.cn/search?containerid=100103type%3D1%26t%3D10%26q%3D%23大学生贩卖自己身份信息成逃犯%23",
            "title": "大学生贩卖自己身份信息成逃犯"
        },
        {
            "id": 33,
            "url": "https://m.weibo.cn/search?containerid=100103type%3D1%26t%3D10%26q%3D%23英国奥运选手抱怨札幌吃住条件太差%23",
            "title": "英国奥运选手抱怨札幌吃住条件太差"
        },
        {
            "id": 34,
            "url": "https://m.weibo.cn/search?containerid=100103type%3D1%26t%3D10%26q%3D%23喻言看甜妹视频笑疯了%23",
            "title": "喻言看甜妹视频笑疯了"
        },
        {
            "id": 35,
            "url": "https://m.weibo.cn/search?containerid=100103type%3D1%26t%3D10%26q%3D%23张哲瀚发微博为冯珊珊庆生%23",
            "title": "张哲瀚发微博为冯珊珊庆生"
        },
        {
            "id": 36,
            "url": "https://m.weibo.cn/search?containerid=100103type%3D1%26t%3D10%26q%3D%23微博上线新表情苦涩%23",
            "title": "微博上线新表情苦涩"
        },
        {
            "id": 37,
            "url": "https://m.weibo.cn/search?containerid=100103type%3D1%26t%3D10%26q%3D%23疫苗对德尔塔变异株仍有良好防护作用%23",
            "title": "疫苗对德尔塔变异株仍有良好防护作用"
        },
        {
            "id": 38,
            "url": "https://m.weibo.cn/search?containerid=100103type%3D1%26t%3D10%26q%3D%23奥运会上的神奇大逆转%23",
            "title": "奥运会上的神奇大逆转"
        },
        {
            "id": 39,
            "url": "https://m.weibo.cn/search?containerid=100103type%3D1%26t%3D10%26q%3D%23北京冰雹%23",
            "title": "北京冰雹"
        },
        {
            "id": 40,
            "url": "https://m.weibo.cn/search?containerid=100103type%3D1%26t%3D10%26q%3D%23跟樊振东学习说话的技巧%23",
            "title": "跟樊振东学习说话的技巧"
        },
        {
            "id": 41,
            "url": "https://m.weibo.cn/search?containerid=100103type%3D1%26t%3D10%26q%3D%23全红婵夺金后发现王者只能玩1小时%23",
            "title": "全红婵夺金后发现王者只能玩1小时"
        },
        {
            "id": 42,
            "url": "https://m.weibo.cn/search?containerid=100103type%3D1%26t%3D10%26q%3D%23电视剧梦醒长安改名与君歌%23",
            "title": "电视剧梦醒长安改名与君歌"
        },
        {
            "id": 43,
            "url": "https://m.weibo.cn/search?containerid=100103type%3D1%26t%3D10%26q%3D%23荆门新增2例本土确诊%23",
            "title": "荆门新增2例本土确诊"
        },
        {
            "id": 44,
            "url": "https://m.weibo.cn/search?containerid=100103type%3D1%26t%3D10%26q%3D%23今年秋季学期开学安排坚持属地管理原则%23",
            "title": "今年秋季学期开学安排坚持属地管理原则"
        },
        {
            "id": 45,
            "url": "https://m.weibo.cn/search?containerid=100103type%3D1%26t%3D10%26q%3D%23俄罗斯的花样游泳有多强%23",
            "title": "俄罗斯的花样游泳有多强"
        },
        {
            "id": 46,
            "url": "https://m.weibo.cn/search?containerid=100103type%3D1%26t%3D10%26q%3D%23清融西施FMVP皮肤首秀%23",
            "title": "清融西施FMVP皮肤首秀"
        },
        {
            "id": 47,
            "url": "https://m.weibo.cn/search?containerid=100103type%3D1%26t%3D10%26q%3D%23东京赛场9次升起两面五星红旗%23",
            "title": "东京赛场9次升起两面五星红旗"
        },
        {
            "id": 48,
            "url": "https://m.weibo.cn/search?containerid=100103type%3D1%26t%3D10%26q%3D%23郎平寄语中国女排%23",
            "title": "郎平寄语中国女排"
        },
        {
            "id": 49,
            "url": "https://m.weibo.cn/search?containerid=100103type%3D1%26t%3D10%26q%3D%23云南虫谷定档%23",
            "title": "云南虫谷定档"
        },
        {
            "id": 50,
            "url": "https://m.weibo.cn/search?containerid=100103type%3D1%26t%3D10%26q%3D%23密室大逃脱这期太热血了%23",
            "title": "密室大逃脱这期太热血了"
        }
    ]
}